har2case/__about__.py
har2case/__init__.py
har2case/cli.py
har2case/compat.py
har2case/core.py
har2case/utils.py
tests/__init__.py
tests/test_har.py
tests/test_utils.py
har2case-0.3.1.dist-info/LICENSE
har2case-0.3.1.dist-info/METADATA
har2case-0.3.1.dist-info/WHEEL
har2case-0.3.1.dist-info/entry_points.txt
har2case-0.3.1.dist-info/top_level.txt
har2case-0.3.1.dist-info/RECORD
